mgquant-3.2.0.dist-info/top_level.txt
mgquant-3.2.0.dist-info/RECORD
mgquant-3.2.0.dist-info/LICENSE
mgquant-3.2.0.dist-info/METADATA
mgquant-3.2.0.dist-info/entry_points.txt
mgquant-3.2.0.dist-info/WHEEL
mgquant/user_module.cpython-312-x86_64-linux-gnu.so
mgquant/interface.cpython-312-x86_64-linux-gnu.so
mgquant/VERSION.txt
mgquant/events.cpython-312-x86_64-linux-gnu.so
mgquant/__init__.py
mgquant/environment.cpython-312-x86_64-linux-gnu.so
mgquant/__main__.py
mgquant/execution_context.cpython-312-x86_64-linux-gnu.so
mgquant/const.cpython-312-x86_64-linux-gnu.so
mgquant/config.yml
mgquant/mod_config.yml
mgquant/main.cpython-312-x86_64-linux-gnu.so
mgquant/resource/__init__.py
mgquant/core/global_var.cpython-312-x86_64-linux-gnu.so
mgquant/core/strategy_loader.cpython-312-x86_64-linux-gnu.so
mgquant/core/bar_dict_price_board.cpython-312-x86_64-linux-gnu.so
mgquant/core/executor.cpython-312-x86_64-linux-gnu.so
mgquant/core/strategy_universe.cpython-312-x86_64-linux-gnu.so
mgquant/core/__init__.py
mgquant/core/strategy.cpython-312-x86_64-linux-gnu.so
mgquant/core/strategy_context.cpython-312-x86_64-linux-gnu.so
mgquant/mod/utils.cpython-312-x86_64-linux-gnu.so
mgquant/mod/__init__.py
mgquant/utils/mg_json.cpython-312-x86_64-linux-gnu.so
mgquant/utils/exception.cpython-312-x86_64-linux-gnu.so
mgquant/utils/datetime_func.cpython-312-x86_64-linux-gnu.so
mgquant/utils/click_helper.cpython-312-x86_64-linux-gnu.so
mgquant/utils/plot_store.cpython-312-x86_64-linux-gnu.so
mgquant/utils/package_helper.cpython-312-x86_64-linux-gnu.so
mgquant/utils/lazyimport.cpython-312-x86_64-linux-gnu.so
mgquant/utils/repr.cpython-312-x86_64-linux-gnu.so
mgquant/utils/__init__.py
mgquant/utils/transformer.cpython-312-x86_64-linux-gnu.so
mgquant/utils/risk.cpython-312-x86_64-linux-gnu.so
mgquant/utils/arg_checker.cpython-312-x86_64-linux-gnu.so
mgquant/utils/disk_persist_provider.cpython-312-x86_64-linux-gnu.so
mgquant/utils/persisit_helper.cpython-312-x86_64-linux-gnu.so
mgquant/utils/logger.cpython-312-x86_64-linux-gnu.so
mgquant/utils/scheduler.cpython-312-x86_64-linux-gnu.so
mgquant/utils/dict_func.cpython-312-x86_64-linux-gnu.so
