Metadata-Version: 2.1
Name: mgquant
Version: 3.2.0
Summary: MindGo Algorithm Trading System
Home-page: https://quant.10jqka.com.cn
Author: mindgo
Author-email: mindgo@myhexin.com
License: Apache License v2
Classifier: Programming Language :: Python
Classifier: Operating System :: Microsoft :: Windows
Classifier: Operating System :: Unix
Classifier: Programming Language :: Python :: 3.5
Classifier: Programming Language :: Python :: 3.6
Classifier: Programming Language :: Python :: 3.7
Classifier: Programming Language :: Python :: 3.8
Classifier: Programming Language :: Python :: 3.9
License-File: LICENSE
Requires-Dist: requests
Requires-Dist: numpy >=1.12.1
Requires-Dist: pandas >=0.20.1
Requires-Dist: python-dateutil >=2.6.0
Requires-Dist: pytz >=2017.2
Requires-Dist: six >=1.10.0
Requires-Dist: pytest >=2.9.2
Requires-Dist: logbook >=1.0.0
Requires-Dist: click >=6.6
Requires-Dist: bcolz-zipline ~=1.2.6
Requires-Dist: matplotlib >=2.0.1
Requires-Dist: jsonpickle >=0.9.4
Requires-Dist: simplejson >=3.10.0
Requires-Dist: XlsxWriter >=0.9.2
Requires-Dist: PyYAML >=3.11
Requires-Dist: ipython
Requires-Dist: tabulate
Requires-Dist: colorama >=0.3.7
